pybgproutesapi/__init__.py
pybgproutesapi/_client.py
pybgproutesapi/_constants.py
pybgproutesapi-0.1.5.dist-info/licenses/LICENSE
pybgproutesapi-0.1.5.dist-info/METADATA
pybgproutesapi-0.1.5.dist-info/WHEEL
pybgproutesapi-0.1.5.dist-info/top_level.txt
pybgproutesapi-0.1.5.dist-info/RECORD
