Metadata-Version: 2.4
Name: pybgproutesapi
Version: 0.1.5
Summary: Python bindings for the bgproutes.io API
Author: Thomas Holterbach and Thomas Alfroy
Author-email: contact@bgproutes.io
Classifier: Programming Language :: Python :: 3
Classifier: Operating System :: OS Independent
Requires-Python: >=3.7
License-File: LICENSE
Requires-Dist: requests>=2.25.0
Dynamic: author
Dynamic: author-email
Dynamic: classifier
Dynamic: license-file
Dynamic: requires-dist
Dynamic: requires-python
Dynamic: summary
